dj_toml_settings/__init__.py
dj_toml_settings/config.py
dj_toml_settings/exceptions.py
dj_toml_settings/toml_parser.py
dj_toml_settings/value_parsers/__init__.py
dj_toml_settings/value_parsers/dict_parsers.py
dj_toml_settings/value_parsers/str_parsers.py
dj_toml_settings-0.5.0.dist-info/WHEEL
dj_toml_settings-0.5.0.dist-info/METADATA
dj_toml_settings-0.5.0.dist-info/RECORD
