Metadata-Version: 2.3
Name: dj-toml-settings
Version: 0.5.0
Summary: Load Django settings from a TOML file
Keywords: django,web,toml
Author: Adam Hill
Author-email: Adam Hill <adam@adamghill.com>
License: The MIT License (MIT)
Classifier: Development Status :: 3 - Alpha
Classifier: Framework :: Django
Classifier: Framework :: Django :: 3.2
Classifier: Framework :: Django :: 4.0
Classifier: Framework :: Django :: 4.1
Classifier: Framework :: Django :: 4.2
Classifier: Intended Audience :: Developers
Classifier: License :: OSI Approved :: MIT License
Classifier: Programming Language :: Python :: 3.10
Classifier: Programming Language :: Python :: 3.11
Classifier: Topic :: Software Development :: Libraries :: Python Modules
Requires-Dist: python-dateutil>=2.9.0.post0
Requires-Dist: tomli>=1.1.0 ; python_full_version < '3.11'
Requires-Dist: typeguard>=2
Requires-Python: >=3.10
Project-URL: homepage, https://github.com/adamghill/dj-toml-settings/
Project-URL: repository, https://github.com/adamghill/dj-toml-settings.git
